{
  "name": "Texture Test",
  "type": "TexturedTemporal",
  "blocks": [
    "Lifecycle",
    "Triangle Vector Field",
    "Global Wind",
    "Follow Colour Curve",
    "Follow Velocity",
    "Initial State",
    "Texture Spawn",
    "Texture Colour",
    "Transform Position"
  ],
  "curve": {
    "items": [
      {
        "item": [
          1.0,
          1.0,
          1.0,
          1.0
        ],
        "value": 0.0
      },
      {
        "item": [
          1.0,
          1.0,
          1.0,
          0.0
        ],
        "value": 10.0
      }
    ],
    "min": 0.0,
    "max": 10.0
  },
  "size": {
    "x": 512,
    "y": 512
  },
  "texturePath": "textures/swiss2.jpg",
  "maskChannel": 0,
  "loopingBehaviour": "Forever",
  "duration": 10.0,
  "particleCount": 100000,
  "spawnOverTime": 10.0
}